{
    "$schema": "https://mintlify.com/schema.json",
    "name": "Starter Kit",
    "logo": {
        "dark": "/sumtyme white.svg",
        "light": "/sumtyme black.svg"
    },
    "favicon": "/s.svg",
    "colors": {
        "primary": "#0D9373",
        "light": "#141616",
        "dark": "#dcdcdc",
        "anchors": {
            "from": "#0D9373",
            "to": "#07C983"
        }
    },
    "topbarLinks": [{
        "name": "Support",
        "url": "mailto:hello@sumtyme.ai"
    }, {
        "name": "Demo",
        "url": "https://genesis-demo.streamlit.app"
    }],


    "navigation": [{
        "group": "sumtyme.ai",
        "pages": [
            "About",
            "Model Library",
            "API Guidance",
            "FAQ"
        ]
    }]

}